elpis/__init__.py
elpis/datasets/__init__.py
elpis/datasets/clean_text.py
elpis/datasets/dataset.py
elpis/datasets/extract_annotations.py
elpis/datasets/preprocessing.py
elpis/datasets/processing.py
elpis/models/__init__.py
elpis/models/annotation.py
elpis/models/elan_options.py
elpis/models/job.py
elpis/models/vocab.py
elpis/trainer/__init__.py
elpis/trainer/data_collator.py
elpis/trainer/metrics.py
elpis/trainer/trainer.py
elpis/trainer/utils.py
elpis/transcriber/__init__.py
elpis/transcriber/results.py
elpis/transcriber/transcribe.py
elpis/utils/audio.py
elpis-0.2.2.dist-info/WHEEL
elpis-0.2.2.dist-info/METADATA
elpis-0.2.2.dist-info/RECORD
