Metadata-Version: 2.1
Name: elpis
Version: 0.2.2
Summary: A library to perform automatic speech recognition with huggingface transformers.
Home-page: https://github.com/CoEDL/elpis_lib
Keywords: Elpis,huggingface,ASR,Automatic Speech Recognition,CoEDL
Author: Harry Keightley
Author-email: harrykeightley@outlook.com
Requires-Python: >=3.10,<4.0
Classifier: Programming Language :: Python :: 3
Classifier: Programming Language :: Python :: 3.10
Classifier: Programming Language :: Python :: 3.11
Requires-Dist: accelerate (>=0.22.0,<0.23.0)
Requires-Dist: datasets (>=2.6.1,<3.0.0)
Requires-Dist: evaluate (>=0.4.0,<0.5.0)
Requires-Dist: jiwer (>=3.0.3,<4.0.0)
Requires-Dist: librosa (>=0.9.2,<0.10.0)
Requires-Dist: loguru (>=0.6.0,<0.7.0)
Requires-Dist: pedalboard (>=0.8.3,<0.9.0)
Requires-Dist: pympi-ling (>=1.70.2,<2.0.0)
Requires-Dist: sounddevice (>=0.4.6,<0.5.0)
Requires-Dist: torch (>=2.0.0,!=2.0.1,!=2.1.0)
Requires-Dist: transformers (>=4.34.0,<5.0.0)
Project-URL: Repository, https://github.com/CoEDL/elpis_lib
